p2p_crypto/__init__.py
p2p_crypto/binance.py
p2p_crypto/config.py
p2p_crypto/prettify.py
p2p_crypto/user_agent.py
p2p_crypto/version.py
p2p_crypto/tests/__init__.py
p2p_crypto/tests/test_binance.py
tests/__init__.py
tests/test_price.py
p2p_crypto-0.0.1.dist-info/LICENSE
p2p_crypto-0.0.1.dist-info/METADATA
p2p_crypto-0.0.1.dist-info/WHEEL
p2p_crypto-0.0.1.dist-info/top_level.txt
p2p_crypto-0.0.1.dist-info/RECORD
